llama_index/retrievers/kendra/__init__.py
llama_index/retrievers/kendra/base.py
llama_index_retrievers_kendra-0.2.1.dist-info/METADATA
llama_index_retrievers_kendra-0.2.1.dist-info/WHEEL
llama_index_retrievers_kendra-0.2.1.dist-info/licenses/LICENSE
llama_index_retrievers_kendra-0.2.1.dist-info/RECORD
