Metadata-Version: 2.4
Name: llama-index-retrievers-kendra
Version: 0.2.1
Summary: llama-index retrievers kendra integration
Author-email: Your Name <you@example.com>
License-Expression: MIT
License-File: LICENSE
Requires-Python: <4.0,>=3.9
Requires-Dist: aioboto3
Requires-Dist: boto3
Requires-Dist: llama-index-core<0.15,>=0.13.0
